agent_session_viewer/__init__.py
agent_session_viewer/db.py
agent_session_viewer/main.py
agent_session_viewer/parser.py
agent_session_viewer/sync.py
agent_session_viewer/static/index.html
agent_session_viewer/static/fonts/MesloLGS-NF-Regular.ttf
agent_session_viewer-0.3.2.dist-info/METADATA
agent_session_viewer-0.3.2.dist-info/WHEEL
agent_session_viewer-0.3.2.dist-info/entry_points.txt
agent_session_viewer-0.3.2.dist-info/licenses/LICENSE
agent_session_viewer-0.3.2.dist-info/RECORD
