Metadata-Version: 2.4
Name: agent-session-viewer
Version: 0.3.2
Summary: A web viewer for AI agent coding sessions (Claude Code, Codex, etc.)
License-Expression: MIT
License-File: LICENSE
Requires-Python: >=3.10
Requires-Dist: apscheduler>=3.10.0
Requires-Dist: fastapi>=0.109.0
Requires-Dist: python-multipart>=0.0.6
Requires-Dist: uvicorn[standard]>=0.27.0
Provides-Extra: dev
Requires-Dist: pytest-asyncio>=0.23.0; extra == 'dev'
Requires-Dist: pytest>=8.0.0; extra == 'dev'
